{
  "301117": [
    {
      "code": "301117",
      "name": "佳缘科技",
      "time": "11:23",
      "price": 47.3,
      "open": 52.45,
      "high": 52.48,
      "low": 46.8,
      "prev_close": 52.45,
      "change_pct": -9.82,
      "volume": 79377.0,
      "amount": 388875148.37,
      "turnover": 0.02,
      "main_inflow": -78827035.59,
      "super_inflow": 345013867.64,
      "big_inflow": -9565354.52,
      "main_control": 0.152778411,
      "pe": -479.05,
      "pb": 4.68
    },
    {
      "code": "301117",
      "name": "佳缘科技",
      "time": "14:27",
      "price": 47.64,
      "open": 52.45,
      "high": 52.48,
      "low": 46.8,
      "prev_close": 52.45,
      "change_pct": -9.17,
      "volume": 106992.0,
      "amount": 520045633.29,
      "turnover": 0.02,
      "main_inflow": -78827035.59,
      "super_inflow": 345013867.64,
      "big_inflow": -9565354.52,
      "main_control": 0.152778411,
      "pe": -482.49,
      "pb": 4.71
    }
  ],
  "301136": [
    {
      "code": "301136",
      "name": "招标股份",
      "time": "11:23",
      "price": 16.28,
      "open": 16.3,
      "high": 16.59,
      "low": 16.2,
      "prev_close": 16.27,
      "change_pct": 0.06,
      "volume": 26437.0,
      "amount": 43367777.0,
      "turnover": 0.02,
      "main_inflow": 83618210.35,
      "super_inflow": 587769915.95,
      "big_inflow": 7182703.45,
      "main_control": 0.010836981,
      "pe": 467.83,
      "pb": 3.07
    },
    {
      "code": "301136",
      "name": "招标股份",
      "time": "14:27",
      "price": 16.44,
      "open": 16.3,
      "high": 16.59,
      "low": 16.2,
      "prev_close": 16.27,
      "change_pct": 1.04,
      "volume": 33942.0,
      "amount": 55652808.0,
      "turnover": 0.02,
      "main_inflow": 83618210.35,
      "super_inflow": 587769915.95,
      "big_inflow": 7182703.45,
      "main_control": 0.010836981,
      "pe": 472.42,
      "pb": 3.1
    }
  ]
}